{
    "users": [
        {
            "user": "scs",
            "password": "scs",
            "department": "customer"
        },
        {
            "user": "fin",
            "password": "fin",
            "department": "finance"
        },
        {
            "user": "prod",
            "password": "prod",
            "department": "product"
        },
        {
            "user": "serv",
            "password": "serv",
            "department": "service"
        },
        {
            "user": "photo",
            "password": "photo",
            "department": "photography"
        },
        {
            "user": "chef",
            "password": "chef",
            "department": "chef"
        },
        {
            "user": "admin",
            "password": "admin",
            "department": "administration"
        },
        {
            "user": "hr",
            "password": "hr",
            "department": "human-resources"
        }
    ]
}